photo_cleanup/__init__.py
photo_cleanup/main.py
photo_cleanup-0.1.7.dist-info/LICENSE
photo_cleanup-0.1.7.dist-info/METADATA
photo_cleanup-0.1.7.dist-info/WHEEL
photo_cleanup-0.1.7.dist-info/entry_points.txt
photo_cleanup-0.1.7.dist-info/RECORD
