Metadata-Version: 2.3
Name: photo-cleanup
Version: 0.1.7
Summary: Photo cleanup tool. Recursively deletes unnecessary JPG files in a folder when a matching RAW file exists
License: MIT
Author: Natalie Albers
Author-email: nralbers@gmail.com
Requires-Python: >=3.13
Classifier: License :: OSI Approved :: MIT License
Classifier: Programming Language :: Python :: 3
Classifier: Programming Language :: Python :: 3.13
Requires-Dist: typer (>=0.15.1,<0.16.0)
Project-URL: Issues, https://github.com/nralbers/photo-cleanup/issues
Project-URL: Repository, https://github.com/nralbers/photo-cleanup
